Metadata-Version: 2.1
Name: gns-sdk-lyb
Version: 0.1.0
Summary: General Notification System Client SDK
Home-page: https://github.com/yourusername/gns
Author: Your Name
Author-email: your.email@example.com
Classifier: Programming Language :: Python :: 3
Classifier: License :: OSI Approved :: MIT License
Classifier: Operating System :: OS Independent
Requires-Python: >=3.7
Requires-Dist: requests >=2.25.0
